{
  "RITES.NSE": {
    "price": 199.65,
    "name": "Rites Ltd",
    "week_52_high": 316,
    "week_52_low": 194.65,
    "day_change": -0.06,
    "day_change_pct": -0.03,
    "week_change_pct": -3.37,
    "month_change_pct": -11.72,
    "volume": 511723,
    "previous_close": 199.71
  },
  "RALLIS.BSE": {
    "price": 247.2,
    "name": "Rallis India Ltd",
    "week_52_high": 385.6,
    "week_52_low": 197,
    "day_change": -1.55,
    "day_change_pct": -0.62,
    "week_change_pct": -3.96,
    "month_change_pct": -8.78,
    "volume": 7589,
    "previous_close": 248.75
  },
  "PIIND.BSE": {
    "price": 2941.0,
    "name": "PI Industries Ltd",
    "week_52_high": 4329,
    "week_52_low": 2941,
    "day_change": -69.95,
    "day_change_pct": -2.32,
    "week_change_pct": -4.09,
    "month_change_pct": -10.05,
    "volume": 3257,
    "previous_close": 3010.95
  },
  "ONGC.BSE": {
    "price": 270.45,
    "name": "ONGC",
    "week_52_high": 293.15,
    "week_52_low": 195.5,
    "day_change": -0.3,
    "day_change_pct": -0.11,
    "week_change_pct": -3.03,
    "month_change_pct": 0.8,
    "volume": 644279,
    "previous_close": 270.75
  },
  "OIL.NSE": {
    "price": 479.3,
    "name": "Oil India Ltd",
    "week_52_high": 524,
    "week_52_low": 325,
    "day_change": -3.4,
    "day_change_pct": -0.7,
    "week_change_pct": -1.07,
    "month_change_pct": 0.01,
    "volume": 5799980,
    "previous_close": 482.7
  },
  "RELIANCE.BSE": {
    "price": 1391.85,
    "name": "Reliance Industries Ltd",
    "week_52_high": 1611.2,
    "week_52_low": 1115.55,
    "day_change": 0.75,
    "day_change_pct": 0.05,
    "week_change_pct": -0.95,
    "month_change_pct": -5.22,
    "volume": 1733925,
    "previous_close": 1391.1
  },
  "SBILIFE.NSE": {
    "price": 1939.4,
    "name": "SBI Life Insurance Company Ltd",
    "week_52_high": 2132,
    "week_52_low": 1382.65,
    "day_change": 0.8,
    "day_change_pct": 0.04,
    "week_change_pct": -0.11,
    "month_change_pct": -4.29,
    "volume": 868643,
    "previous_close": 1938.6
  },
  "RAILTEL.NSE": {
    "price": 287.1,
    "name": "Railtel Corporation of India Ltd",
    "week_52_high": 478.95,
    "week_52_low": 266,
    "day_change": 3.6,
    "day_change_pct": 1.27,
    "week_change_pct": -1.31,
    "month_change_pct": -15.41,
    "volume": 978673,
    "previous_close": 283.5
  },
  "RVNL.BSE": {
    "price": 279.5,
    "name": "Rail Vikas Nigam",
    "week_52_high": 448,
    "week_52_low": 270.95,
    "day_change": 2.0,
    "day_change_pct": 0.72,
    "week_change_pct": -2.24,
    "month_change_pct": -11.7,
    "volume": 611964,
    "previous_close": 277.5
  },
  "RALLIS.NSE": {
    "price": 247.35,
    "name": "Rallis India Ltd",
    "week_52_high": 385.9,
    "week_52_low": 196.78,
    "day_change": -1.25,
    "day_change_pct": -0.5,
    "week_change_pct": -3.83,
    "month_change_pct": -8.73,
    "volume": 156641,
    "previous_close": 248.6
  },
  "RITES.BSE": {
    "price": 200.15,
    "name": "Rites Ltd",
    "week_52_high": 316.15,
    "week_52_low": 194.65,
    "day_change": 0.75,
    "day_change_pct": 0.38,
    "week_change_pct": -3.13,
    "month_change_pct": -11.57,
    "volume": 43402,
    "previous_close": 199.4
  },
  "PIIND.NSE": {
    "price": 2952.4,
    "name": "PI Industries Ltd",
    "week_52_high": 4330,
    "week_52_low": 2940.1,
    "day_change": -59.9,
    "day_change_pct": -1.99,
    "week_change_pct": -4.13,
    "month_change_pct": -10.02,
    "volume": 196476,
    "previous_close": 3012.3
  },
  "ONGC.NSE": {
    "price": 270.55,
    "name": "ONGC",
    "week_52_high": 293,
    "week_52_low": 195.5,
    "day_change": -0.2,
    "day_change_pct": -0.07,
    "week_change_pct": -3.01,
    "month_change_pct": 0.84,
    "volume": 20059801,
    "previous_close": 270.75
  },
  "RELIANCE.NSE": {
    "price": 1392.2,
    "name": "Reliance Industries Ltd",
    "week_52_high": 1611.8,
    "week_52_low": 1114.85,
    "day_change": 2.0,
    "day_change_pct": 0.14,
    "week_change_pct": -0.9,
    "month_change_pct": -5.21,
    "volume": 20939959,
    "previous_close": 1390.2
  },
  "SBILIFE.BSE": {
    "price": 1940.3,
    "name": "SBI Life Insurance Company Ltd",
    "week_52_high": 2132.9,
    "week_52_low": 1382,
    "day_change": 3.5,
    "day_change_pct": 0.18,
    "week_change_pct": 0.03,
    "month_change_pct": -4.27,
    "volume": 11740,
    "previous_close": 1936.8
  },
  "RVNL.NSE": {
    "price": 279.6,
    "name": "Rail Vikas Nigam",
    "week_52_high": 447.8,
    "week_52_low": 270.95,
    "day_change": 2.4,
    "day_change_pct": 0.87,
    "week_change_pct": -2.24,
    "month_change_pct": -11.67,
    "volume": 6945305,
    "previous_close": 277.2
  },
  "RAILTEL.BSE": {
    "price": 287.0,
    "name": "Railtel Corporation of India Ltd",
    "week_52_high": 478.8,
    "week_52_low": 265.6,
    "day_change": 3.55,
    "day_change_pct": 1.25,
    "week_change_pct": -1.41,
    "month_change_pct": -15.44,
    "volume": 76882,
    "previous_close": 283.45
  },
  "SBIN.NSE": {
    "price": 1085.2,
    "name": "State Bank of India",
    "week_52_high": 1234.7,
    "week_52_low": 722.3,
    "day_change": -5.9,
    "day_change_pct": -0.54,
    "week_change_pct": -5.06,
    "month_change_pct": -8.26,
    "volume": 14614140,
    "previous_close": 1091.1
  },
  "SUNTV.NSE": {
    "price": 593.3,
    "name": "Sun TV Network Ltd",
    "week_52_high": 691.4,
    "week_52_low": 480.2,
    "day_change": 15.3,
    "day_change_pct": 2.65,
    "week_change_pct": -1.12,
    "month_change_pct": -3.24,
    "volume": 220104,
    "previous_close": 578.0
  },
  "AFCONS.NSE": {
    "price": 278.5,
    "name": "Afcons Infrastructure Ltd",
    "week_52_high": 498.7,
    "week_52_low": 271.5,
    "day_change": -1.8,
    "day_change_pct": -0.64,
    "week_change_pct": -1.61,
    "month_change_pct": -18.59,
    "volume": 459609,
    "previous_close": 280.3
  },
  "IREDA.NSE": {
    "price": 117.03,
    "name": "Indian Renewable Energy Dev Agency Ltd",
    "week_52_high": 186.58,
    "week_52_low": 112.07,
    "day_change": 2.23,
    "day_change_pct": 1.94,
    "week_change_pct": -0.21,
    "month_change_pct": -7.61,
    "volume": 9357674,
    "previous_close": 114.8
  },
  "SYNGENE.NSE": {
    "price": 404.1,
    "name": "Syngene International Ltd",
    "week_52_high": 760,
    "week_52_low": 387.05,
    "day_change": -4.05,
    "day_change_pct": -0.99,
    "week_change_pct": 1.1,
    "month_change_pct": -11.21,
    "volume": 632047,
    "previous_close": 408.15
  },
  "IRCTC.BSE": {
    "price": 536.55,
    "name": "Indian Rail Tour Corp Ltd",
    "week_52_high": 820.2,
    "week_52_low": 520.2,
    "day_change": 2.4,
    "day_change_pct": 0.45,
    "week_change_pct": -2.95,
    "month_change_pct": -14.61,
    "volume": 282826,
    "previous_close": 534.15
  },
  "CENTRALBK.NSE": {
    "price": 36.61,
    "name": "Central Bank of India",
    "week_52_high": 47.3,
    "week_52_low": 32.75,
    "day_change": 0.0,
    "day_change_pct": 0.0,
    "week_change_pct": -1.37,
    "month_change_pct": -3.17,
    "volume": 6995129,
    "previous_close": 36.61
  },
  "AUROPHARMA.BSE": {
    "price": 1313.3,
    "name": "Aurobindo Pharma Ltd",
    "week_52_high": 1319.6,
    "week_52_low": 994.35,
    "day_change": 8.7,
    "day_change_pct": 0.67,
    "week_change_pct": 6.63,
    "month_change_pct": 14.6,
    "volume": 79056,
    "previous_close": 1304.6
  },
  "IRB.NSE": {
    "price": 42.57,
    "name": "IRB Infra",
    "week_52_high": 54.28,
    "week_52_low": 38.3,
    "day_change": 0.47,
    "day_change_pct": 1.12,
    "week_change_pct": 4.39,
    "month_change_pct": -4.19,
    "volume": 9720140,
    "previous_close": 42.1
  },
  "TATACAP.NSE": {
    "price": 318.6,
    "name": "TATA Capital",
    "week_52_high": 367.3,
    "week_52_low": 309,
    "day_change": -1.2,
    "day_change_pct": -0.38,
    "week_change_pct": 0.05,
    "month_change_pct": -10.91,
    "volume": 1490019,
    "previous_close": 319.8
  },
  "IRCTC.NSE": {
    "price": 536.7,
    "name": "Indian Rail Tour Corp Ltd",
    "week_52_high": 820.25,
    "week_52_low": 520.05,
    "day_change": 2.55,
    "day_change_pct": 0.48,
    "week_change_pct": -2.91,
    "month_change_pct": -14.59,
    "volume": 3154397,
    "previous_close": 534.15
  },
  "LGEINDIA.BSE": {
    "price": 1572.0,
    "name": "LG Electronics India",
    "week_52_high": 1736.4,
    "week_52_low": 1300.4,
    "day_change": -20.3,
    "day_change_pct": -1.27,
    "week_change_pct": -0.32,
    "month_change_pct": 3.73,
    "volume": 17618,
    "previous_close": 1592.3
  },
  "KAJARIACER.BSE": {
    "price": 939.3,
    "name": "Kajaria Ceramics Ltd",
    "week_52_high": 1322,
    "week_52_low": 745,
    "day_change": -20.15,
    "day_change_pct": -2.1,
    "week_change_pct": 0.53,
    "month_change_pct": -1.64,
    "volume": 47600,
    "previous_close": 959.45
  },
  "HEROMOTOCO.BSE": {
    "price": 5395.6,
    "name": "Hero MotoCorp Ltd",
    "week_52_high": 6390,
    "week_52_low": 3322.6,
    "day_change": -177.85,
    "day_change_pct": -3.19,
    "week_change_pct": -2.05,
    "month_change_pct": -5.03,
    "volume": 31772,
    "previous_close": 5573.45
  },
  "AUROPHARMA.NSE": {
    "price": 1311.9,
    "name": "Aurobindo Pharma Ltd",
    "week_52_high": 1319.8,
    "week_52_low": 1010,
    "day_change": 7.1,
    "day_change_pct": 0.54,
    "week_change_pct": 6.49,
    "month_change_pct": 14.42,
    "volume": 2110239,
    "previous_close": 1304.8
  },
  "JAINREC.BSE": {
    "price": 430.5,
    "name": "Jain Resource Recycling Limited",
    "week_52_high": 461,
    "week_52_low": 247.8,
    "day_change": -3.35,
    "day_change_pct": -0.77,
    "week_change_pct": 3.06,
    "month_change_pct": 8.97,
    "volume": 101795,
    "previous_close": 433.85
  },
  "LGEINDIA.NSE": {
    "price": 1577.0,
    "name": "LG Electronics India",
    "week_52_high": 1749,
    "week_52_low": 1325.5,
    "day_change": -17.6,
    "day_change_pct": -1.1,
    "week_change_pct": -0.17,
    "month_change_pct": 3.83,
    "volume": 274345,
    "previous_close": 1594.6
  },
  "KAJARIACER.NSE": {
    "price": 940.0,
    "name": "Kajaria Ceramics Ltd",
    "week_52_high": 1321.9,
    "week_52_low": 758.7,
    "day_change": -17.95,
    "day_change_pct": -1.87,
    "week_change_pct": 0.57,
    "month_change_pct": -1.75,
    "volume": 537246,
    "previous_close": 957.95
  },
  "HEROMOTOCO.NSE": {
    "price": 5394.5,
    "name": "Hero MotoCorp Ltd",
    "week_52_high": 6388.5,
    "week_52_low": 3344,
    "day_change": -180.5,
    "day_change_pct": -3.24,
    "week_change_pct": -2.14,
    "month_change_pct": -5.07,
    "volume": 476478,
    "previous_close": 5575.0
  },
  "TITAGARH.BSE": {
    "price": 658.9,
    "name": "TITAGARH RAIL SYSTEMS LIMITED",
    "week_52_high": 974.05,
    "week_52_low": 638.4,
    "day_change": 3.3,
    "day_change_pct": 0.5,
    "week_change_pct": -3.41,
    "month_change_pct": -17.67,
    "volume": 43679,
    "previous_close": 655.6
  },
  "TRITURBINE.BSE": {
    "price": 471.3,
    "name": "Triveni Turbine Limited",
    "week_52_high": 675.4,
    "week_52_low": 454.4,
    "day_change": -3.6,
    "day_change_pct": -0.76,
    "week_change_pct": 0.14,
    "month_change_pct": -3.56,
    "volume": 12976,
    "previous_close": 474.9
  },
  "TMPV.NSE": {
    "price": 324.55,
    "name": "Tata Motors Passenger Vehicles Limited",
    "week_52_high": 512.25,
    "week_52_low": 323.35,
    "day_change": -10.8,
    "day_change_pct": -3.22,
    "week_change_pct": -7.47,
    "month_change_pct": -15.64,
    "volume": 9707654,
    "previous_close": 335.35
  },
  "BHARTIARTL.BSE": {
    "price": 1797.4,
    "name": "Bharti Airtel Limited",
    "week_52_high": 2174.7,
    "week_52_low": 1619.95,
    "day_change": -8.6,
    "day_change_pct": -0.48,
    "week_change_pct": -3.78,
    "month_change_pct": -10.54,
    "volume": 1801543,
    "previous_close": 1806.0
  },
  "TRENT.BSE": {
    "price": 3535.0,
    "name": "Trent",
    "week_52_high": 6259,
    "week_52_low": 3503.25,
    "day_change": -89.25,
    "day_change_pct": -2.46,
    "week_change_pct": -5.11,
    "month_change_pct": -16.31,
    "volume": 20043,
    "previous_close": 3624.25
  },
  "ASIANPAINT.BSE": {
    "price": 2223.45,
    "name": "Asian Paints Ltd",
    "week_52_high": 2985.5,
    "week_52_low": 2163,
    "day_change": -8.15,
    "day_change_pct": -0.37,
    "week_change_pct": -2.56,
    "month_change_pct": -7.19,
    "volume": 170487,
    "previous_close": 2231.6
  },
  "JAINREC.NSE": {
    "price": 428.55,
    "name": "Jain Resource Recycling Limited",
    "week_52_high": 461,
    "week_52_low": 247.57,
    "day_change": -5.45,
    "day_change_pct": -1.26,
    "week_change_pct": 3.3,
    "month_change_pct": 9.18,
    "volume": 1732446,
    "previous_close": 434.0
  },
  "TATAPOWER.BSE": {
    "price": 402.3,
    "name": "Tata Power Company Limited",
    "week_52_high": 416.7,
    "week_52_low": 332.1,
    "day_change": 17.1,
    "day_change_pct": 4.44,
    "week_change_pct": 7.15,
    "month_change_pct": 7.19,
    "volume": 2790856,
    "previous_close": 385.2
  },
  "BBTC.BSE": {
    "price": 1569.25,
    "name": "Bombay Burmah Trading Corporation Ltd",
    "week_52_high": 2156.1,
    "week_52_low": 1513.9,
    "day_change": -5.35,
    "day_change_pct": -0.34,
    "week_change_pct": -3.25,
    "month_change_pct": -15.3,
    "volume": 5297,
    "previous_close": 1574.6
  },
  "TITAGARH.NSE": {
    "price": 655.85,
    "name": "TITAGARH RAIL SYSTEMS LIMITED",
    "week_52_high": 974.35,
    "week_52_low": 637.7,
    "day_change": -0.1,
    "day_change_pct": -0.02,
    "week_change_pct": -3.59,
    "month_change_pct": -17.53,
    "volume": 572475,
    "previous_close": 655.95
  },
  "TRITURBINE.NSE": {
    "price": 470.3,
    "name": "Triveni Turbine Limited",
    "week_52_high": 675.2,
    "week_52_low": 454.1,
    "day_change": -4.3,
    "day_change_pct": -0.91,
    "week_change_pct": -0.34,
    "month_change_pct": -3.51,
    "volume": 237577,
    "previous_close": 474.6
  },
  "BHARTIARTL.NSE": {
    "price": 1801.3,
    "name": "Bharti Airtel Limited",
    "week_52_high": 2174.5,
    "week_52_low": 1612.2,
    "day_change": -5.7,
    "day_change_pct": -0.32,
    "week_change_pct": -3.71,
    "month_change_pct": -10.48,
    "volume": 12922735,
    "previous_close": 1807.0
  },
  "ADANIGREEN.BSE": {
    "price": 865.95,
    "name": "Adani Green Energy Limited",
    "week_52_high": 1179.2,
    "week_52_low": 767,
    "day_change": 16.15,
    "day_change_pct": 1.9,
    "week_change_pct": 0.81,
    "month_change_pct": -12.93,
    "volume": 290680,
    "previous_close": 849.8
  },
  "TRENT.NSE": {
    "price": 3533.6,
    "name": "Trent",
    "week_52_high": 6261,
    "week_52_low": 3502.5,
    "day_change": -93.8,
    "day_change_pct": -2.59,
    "week_change_pct": -5.08,
    "month_change_pct": -16.24,
    "volume": 989163,
    "previous_close": 3627.4
  },
  "ASIANPAINT.NSE": {
    "price": 2221.2,
    "name": "Asian Paints Ltd",
    "week_52_high": 2985.7,
    "week_52_low": 2162.6,
    "day_change": -10.8,
    "day_change_pct": -0.48,
    "week_change_pct": -2.56,
    "month_change_pct": -7.16,
    "volume": 1384055,
    "previous_close": 2232.0
  },
  "TEJASNET.BSE": {
    "price": 440.8,
    "name": "Tejas Networks Limited",
    "week_52_high": 914.5,
    "week_52_low": 294.1,
    "day_change": -30.0,
    "day_change_pct": -6.37,
    "week_change_pct": -5.28,
    "month_change_pct": 30.07,
    "volume": 457130,
    "previous_close": 470.8
  },
  "BEML.BSE": {
    "price": 1617.0,
    "name": "BEML Limited",
    "week_52_high": 2437.4,
    "week_52_low": 1232.35,
    "day_change": 11.1,
    "day_change_pct": 0.69,
    "week_change_pct": -2.46,
    "month_change_pct": -8.78,
    "volume": 18944,
    "previous_close": 1605.9
  },
  "HIGHENE.BSE": {
    "price": 546.95,
    "name": "High Energy Batteries (India) Ltd",
    "week_52_high": 830.35,
    "week_52_low": 432,
    "day_change": 0.65,
    "day_change_pct": 0.12,
    "week_change_pct": -1.37,
    "month_change_pct": -4.6,
    "volume": 7932,
    "previous_close": 546.3
  },
  "TATAPOWER.NSE": {
    "price": 402.15,
    "name": "Tata Power Company Limited",
    "week_52_high": 416.8,
    "week_52_low": 335,
    "day_change": 16.4,
    "day_change_pct": 4.25,
    "week_change_pct": 7.1,
    "month_change_pct": 7.05,
    "volume": 25007929,
    "previous_close": 385.75
  },
  "BBTC.NSE": {
    "price": 1570.9,
    "name": "Bombay Burmah Trading Corporation Ltd",
    "week_52_high": 2155,
    "week_52_low": 1511.2,
    "day_change": 0.5,
    "day_change_pct": 0.03,
    "week_change_pct": -3.05,
    "month_change_pct": -15.28,
    "volume": 43038,
    "previous_close": 1570.4
  },
  "NATIONALUM.NSE": {
    "price": 409.15,
    "name": "National Aluminium Company Limited",
    "week_52_high": 431.5,
    "week_52_low": 137.75,
    "day_change": 11.4,
    "day_change_pct": 2.87,
    "week_change_pct": 3.28,
    "month_change_pct": 11.27,
    "volume": 20128518,
    "previous_close": 397.75
  },
  "LT.BSE": {
    "price": 3720.95,
    "name": "Larsen and Toubro Ltd",
    "week_52_high": 4440,
    "week_52_low": 2967.65,
    "day_change": -117.3,
    "day_change_pct": -3.06,
    "week_change_pct": -5.77,
    "month_change_pct": -10.77,
    "volume": 371909,
    "previous_close": 3838.25
  },
  "LICI.BSE": {
    "price": 796.5,
    "name": "Life Insurance Corporation Of India",
    "week_52_high": 980.05,
    "week_52_low": 735,
    "day_change": -5.9,
    "day_change_pct": -0.74,
    "week_change_pct": -3.16,
    "month_change_pct": -9.0,
    "volume": 75543,
    "previous_close": 802.4
  },
  "ADANIGREEN.NSE": {
    "price": 866.55,
    "name": "Adani Green Energy Limited",
    "week_52_high": 1177.55,
    "week_52_low": 765,
    "day_change": 16.9,
    "day_change_pct": 1.99,
    "week_change_pct": 0.95,
    "month_change_pct": -12.89,
    "volume": 6591414,
    "previous_close": 849.65
  },
  "JWL.BSE": {
    "price": 272.35,
    "name": "Jupiter Wagons Limited",
    "week_52_high": 457.2,
    "week_52_low": 237.1,
    "day_change": -3.6,
    "day_change_pct": -1.3,
    "week_change_pct": -9.2,
    "month_change_pct": -12.34,
    "volume": 359366,
    "previous_close": 275.95
  },
  "DIXON.BSE": {
    "price": 10804.5,
    "name": "Dixon Technologies (India) Limited",
    "week_52_high": 18471.5,
    "week_52_low": 9620,
    "day_change": 191.05,
    "day_change_pct": 1.8,
    "week_change_pct": 7.68,
    "month_change_pct": -7.94,
    "volume": 82207,
    "previous_close": 10613.45
  },
  "BEML.NSE": {
    "price": 1614.2,
    "name": "BEML Limited",
    "week_52_high": 2437.4,
    "week_52_low": 1225.6,
    "day_change": 4.1,
    "day_change_pct": 0.25,
    "week_change_pct": -2.38,
    "month_change_pct": -8.68,
    "volume": 216918,
    "previous_close": 1610.1
  },
  "TEJASNET.NSE": {
    "price": 441.1,
    "name": "Tejas Networks Limited",
    "week_52_high": 914.4,
    "week_52_low": 294,
    "day_change": -29.3,
    "day_change_pct": -6.23,
    "week_change_pct": -5.15,
    "month_change_pct": 30.1,
    "volume": 7856082,
    "previous_close": 470.4
  },
  "IOC.NSE": {
    "price": 160.16,
    "name": "Indian Oil Corporation Ltd",
    "week_52_high": 188.96,
    "week_52_low": 116.2,
    "day_change": -0.47,
    "day_change_pct": -0.29,
    "week_change_pct": -5.05,
    "month_change_pct": -11.67,
    "volume": 21636039,
    "previous_close": 160.63
  },
  "IRFC.NSE": {
    "price": 99.92,
    "name": "Indian Railway Fin Corp",
    "week_52_high": 148.95,
    "week_52_low": 95.27,
    "day_change": 0.67,
    "day_change_pct": 0.68,
    "week_change_pct": 0.45,
    "month_change_pct": -12.6,
    "volume": 14255322,
    "previous_close": 99.25
  },
  "TATACHEM.BSE": {
    "price": 683.05,
    "name": "Tata Chemicals",
    "week_52_high": 1026,
    "week_52_low": 675.25,
    "day_change": -5.5,
    "day_change_pct": -0.8,
    "week_change_pct": -3.41,
    "month_change_pct": -3.76,
    "volume": 16348,
    "previous_close": 688.55
  },
  "TMCV.BSE": {
    "price": 443.6,
    "name": "Tata Motors Ltd",
    "week_52_high": 508.95,
    "week_52_low": 306,
    "day_change": -1.95,
    "day_change_pct": -0.44,
    "week_change_pct": -6.41,
    "month_change_pct": -8.93,
    "volume": 1191501,
    "previous_close": 445.55
  },
  "TATATECH.BSE": {
    "price": 552.45,
    "name": "Tata Technologies Ltd",
    "week_52_high": 797,
    "week_52_low": 544.5,
    "day_change": -4.35,
    "day_change_pct": -0.78,
    "week_change_pct": -4.14,
    "month_change_pct": -12.02,
    "volume": 67459,
    "previous_close": 556.8
  },
  "TATASTEEL.BSE": {
    "price": 193.45,
    "name": "Tata Steel Ltd",
    "week_52_high": 216.5,
    "week_52_low": 121.35,
    "day_change": -1.25,
    "day_change_pct": -0.64,
    "week_change_pct": -2.54,
    "month_change_pct": -6.84,
    "volume": 1014876,
    "previous_close": 194.7
  },
  "LT.NSE": {
    "price": 3719.5,
    "name": "Larsen and Toubro Ltd",
    "week_52_high": 4440,
    "week_52_low": 2965.3,
    "day_change": -119.3,
    "day_change_pct": -3.11,
    "week_change_pct": -5.83,
    "month_change_pct": -10.81,
    "volume": 4255443,
    "previous_close": 3838.8
  },
  "IRCON.BSE": {
    "price": 136.5,
    "name": "Ircon International Ltd",
    "week_52_high": 225.7,
    "week_52_low": 130.05,
    "day_change": -0.75,
    "day_change_pct": -0.55,
    "week_change_pct": -7.11,
    "month_change_pct": -12.7,
    "volume": 394544,
    "previous_close": 137.25
  },
  "LICI.NSE": {
    "price": 796.65,
    "name": "Life Insurance Corporation Of India",
    "week_52_high": 980,
    "week_52_low": 734.6,
    "day_change": -5.75,
    "day_change_pct": -0.72,
    "week_change_pct": -3.12,
    "month_change_pct": -8.99,
    "volume": 755710,
    "previous_close": 802.4
  },
  "JWL.NSE": {
    "price": 272.2,
    "name": "Jupiter Wagons Limited",
    "week_52_high": 457,
    "week_52_low": 246.2,
    "day_change": -2.65,
    "day_change_pct": -0.96,
    "week_change_pct": -8.84,
    "month_change_pct": -12.26,
    "volume": 2403341,
    "previous_close": 274.85
  },
  "DIXON.NSE": {
    "price": 10803.0,
    "name": "Dixon Technologies (India) Limited",
    "week_52_high": 18471,
    "week_52_low": 9630,
    "day_change": 185.0,
    "day_change_pct": 1.74,
    "week_change_pct": 7.72,
    "month_change_pct": -7.99,
    "volume": 968428,
    "previous_close": 10618.0
  },
  "TATACHEM.NSE": {
    "price": 683.15,
    "name": "Tata Chemicals",
    "week_52_high": 1026.65,
    "week_52_low": 675.6,
    "day_change": -5.65,
    "day_change_pct": -0.82,
    "week_change_pct": -3.39,
    "month_change_pct": -3.73,
    "volume": 330591,
    "previous_close": 688.8
  },
  "ADANIPOWER.BSE": {
    "price": 149.1,
    "name": "Adani Power Limited",
    "week_52_high": 182.75,
    "week_52_low": 94.4,
    "day_change": 10.25,
    "day_change_pct": 7.38,
    "week_change_pct": 7.34,
    "month_change_pct": -1.16,
    "volume": 5299147,
    "previous_close": 138.85
  },
  "TMCV.NSE": {
    "price": 443.55,
    "name": "Tata Motors Ltd",
    "week_52_high": 509,
    "week_52_low": 306.3,
    "day_change": -1.9,
    "day_change_pct": -0.43,
    "week_change_pct": -6.47,
    "month_change_pct": -8.96,
    "volume": 12285760,
    "previous_close": 445.45
  },
  "TATATECH.NSE": {
    "price": 551.85,
    "name": "Tata Technologies Ltd",
    "week_52_high": 797,
    "week_52_low": 544.45,
    "day_change": -5.05,
    "day_change_pct": -0.91,
    "week_change_pct": -4.28,
    "month_change_pct": -12.12,
    "volume": 822824,
    "previous_close": 556.9
  },
  "ITC.BSE": {
    "price": 303.9,
    "name": "ITC Ltd",
    "week_52_high": 435.05,
    "week_52_low": 295.8,
    "day_change": -5.05,
    "day_change_pct": -1.63,
    "week_change_pct": -1.89,
    "month_change_pct": -4.49,
    "volume": 451148,
    "previous_close": 308.95
  },
  "TATASTEEL.NSE": {
    "price": 193.47,
    "name": "Tata Steel Ltd",
    "week_52_high": 216.45,
    "week_52_low": 122.44,
    "day_change": -1.27,
    "day_change_pct": -0.65,
    "week_change_pct": -2.51,
    "month_change_pct": -6.8,
    "volume": 24413736,
    "previous_close": 194.74
  },
  "ITCHOTELS.BSE": {
    "price": 158.1,
    "name": "ITC Hotels Ltd",
    "week_52_high": 261.35,
    "week_52_low": 156.65,
    "day_change": -3.9,
    "day_change_pct": -2.41,
    "week_change_pct": -5.22,
    "month_change_pct": -16.28,
    "volume": 186559,
    "previous_close": 162.0
  },
  "JIOFIN.BSE": {
    "price": 242.3,
    "name": "Jio Financial Services Ltd",
    "week_52_high": 338.45,
    "week_52_low": 200.15,
    "day_change": 3.65,
    "day_change_pct": 1.53,
    "week_change_pct": 1.21,
    "month_change_pct": -10.34,
    "volume": 622541,
    "previous_close": 238.65
  },
  "IRCON.NSE": {
    "price": 136.55,
    "name": "Ircon International Ltd",
    "week_52_high": 225.52,
    "week_52_low": 130,
    "day_change": -0.61,
    "day_change_pct": -0.44,
    "week_change_pct": -7.08,
    "month_change_pct": -12.71,
    "volume": 3202461,
    "previous_close": 137.16
  },
  "AWHCL.BSE": {
    "price": 485.9,
    "name": "Antony Waste Handling Cell Ltd",
    "week_52_high": 692.05,
    "week_52_low": 407.5,
    "day_change": 8.85,
    "day_change_pct": 1.86,
    "week_change_pct": 1.51,
    "month_change_pct": -8.83,
    "volume": 6274,
    "previous_close": 477.05
  },
  "WABAG.BSE": {
    "price": 1275.85,
    "name": "Va Tech Wabag Ltd",
    "week_52_high": 1679,
    "week_52_low": 1033.95,
    "day_change": 22.7,
    "day_change_pct": 1.81,
    "week_change_pct": 4.24,
    "month_change_pct": -2.9,
    "volume": 48887,
    "previous_close": 1253.15
  },
  "IDEA.NSE": {
    "price": 9.56,
    "name": "Vodafone Idea Limited",
    "week_52_high": 12.8,
    "week_52_low": 6.12,
    "day_change": -0.15,
    "day_change_pct": -1.54,
    "week_change_pct": -4.97,
    "month_change_pct": -19.32,
    "volume": 444257788,
    "previous_close": 9.71
  },
  "BHARATCOAL.NSE": {
    "price": 35.81,
    "name": "Bharat Coking Coal Limited",
    "week_52_high": 45.09,
    "week_52_low": 31.16,
    "day_change": 2.46,
    "day_change_pct": 7.38,
    "week_change_pct": 8.61,
    "month_change_pct": -2.4,
    "volume": 62076847,
    "previous_close": 33.35
  },
  "ADANIPOWER.NSE": {
    "price": 149.11,
    "name": "Adani Power Limited",
    "week_52_high": 182.7,
    "week_52_low": 92.4,
    "day_change": 10.26,
    "day_change_pct": 7.39,
    "week_change_pct": 7.28,
    "month_change_pct": -1.19,
    "volume": 81276272,
    "previous_close": 138.85
  },
  "AFCONS.BSE": {
    "price": 279.2,
    "name": "Afcons Infrastructure Ltd",
    "week_52_high": 498.9,
    "week_52_low": 271.65,
    "day_change": -1.1,
    "day_change_pct": -0.39,
    "week_change_pct": -1.57,
    "month_change_pct": -18.76,
    "volume": 958503,
    "previous_close": 280.3
  },
  "IREDA.BSE": {
    "price": 117.1,
    "name": "Indian Renewable Energy Dev Agency Ltd",
    "week_52_high": 186.55,
    "week_52_low": 111.75,
    "day_change": 2.15,
    "day_change_pct": 1.87,
    "week_change_pct": -0.13,
    "month_change_pct": -7.54,
    "volume": 1138557,
    "previous_close": 114.95
  },
  "ITC.NSE": {
    "price": 304.1,
    "name": "ITC Ltd",
    "week_52_high": 435.1,
    "week_52_low": 295.8,
    "day_change": -4.9,
    "day_change_pct": -1.59,
    "week_change_pct": -1.81,
    "month_change_pct": -4.45,
    "volume": 23319679,
    "previous_close": 309.0
  },
  "SYNGENE.BSE": {
    "price": 403.9,
    "name": "Syngene International Ltd",
    "week_52_high": 760.95,
    "week_52_low": 381.05,
    "day_change": -3.6,
    "day_change_pct": -0.88,
    "week_change_pct": 1.24,
    "month_change_pct": -11.23,
    "volume": 9639,
    "previous_close": 407.5
  },
  "ITCHOTELS.NSE": {
    "price": 157.96,
    "name": "ITC Hotels Ltd",
    "week_52_high": 261.62,
    "week_52_low": 156.6,
    "day_change": -4.16,
    "day_change_pct": -2.57,
    "week_change_pct": -5.6,
    "month_change_pct": -16.38,
    "volume": 5350511,
    "previous_close": 162.12
  },
  "JIOFIN.NSE": {
    "price": 242.2,
    "name": "Jio Financial Services Ltd",
    "week_52_high": 338.6,
    "week_52_low": 203.1,
    "day_change": 3.5,
    "day_change_pct": 1.47,
    "week_change_pct": 1.19,
    "month_change_pct": -10.4,
    "volume": 18865160,
    "previous_close": 238.7
  },
  "AWHCL.NSE": {
    "price": 485.45,
    "name": "Antony Waste Handling Cell Ltd",
    "week_52_high": 693,
    "week_52_low": 408.05,
    "day_change": 9.0,
    "day_change_pct": 1.89,
    "week_change_pct": 1.81,
    "month_change_pct": -8.46,
    "volume": 106464,
    "previous_close": 476.45
  },
  "WABAG.NSE": {
    "price": 1279.5,
    "name": "Va Tech Wabag Ltd",
    "week_52_high": 1680,
    "week_52_low": 1033,
    "day_change": 27.6,
    "day_change_pct": 2.2,
    "week_change_pct": 4.45,
    "month_change_pct": -2.57,
    "volume": 869900,
    "previous_close": 1251.9
  },
  "BIOCON.NSE": {
    "price": 392.2,
    "name": "Biocon Ltd",
    "week_52_high": 424.95,
    "week_52_low": 299,
    "day_change": -3.15,
    "day_change_pct": -0.8,
    "week_change_pct": 0.38,
    "month_change_pct": 4.53,
    "volume": 1921703,
    "previous_close": 395.35
  },
  "TATACAP.BSE": {
    "price": 318.5,
    "name": "TATA Capital",
    "week_52_high": 367.65,
    "week_52_low": 309.1,
    "day_change": -1.15,
    "day_change_pct": -0.36,
    "week_change_pct": 0.03,
    "month_change_pct": -10.91,
    "volume": 93136,
    "previous_close": 319.65
  },
  "ASHOKLEY.NSE": {
    "price": 178.47,
    "name": "Ashok Leyland Ltd",
    "week_52_high": 215.42,
    "week_52_low": 95.95,
    "day_change": -6.19,
    "day_change_pct": -3.35,
    "week_change_pct": -8.32,
    "month_change_pct": -13.51,
    "volume": 44243228,
    "previous_close": 184.66
  },
  "VEDL.NSE": {
    "price": 719.6,
    "name": "Vedanta Limited",
    "week_52_high": 769.8,
    "week_52_low": 350.1,
    "day_change": -1.95,
    "day_change_pct": -0.27,
    "week_change_pct": -0.19,
    "month_change_pct": 2.63,
    "volume": 10180516,
    "previous_close": 721.55
  }
}